winzy_banner/__init__.py
winzy_banner-0.1.5.dist-info/LICENSE
winzy_banner-0.1.5.dist-info/METADATA
winzy_banner-0.1.5.dist-info/WHEEL
winzy_banner-0.1.5.dist-info/entry_points.txt
winzy_banner-0.1.5.dist-info/top_level.txt
winzy_banner-0.1.5.dist-info/RECORD
