Metadata-Version: 2.1
Name: winzy-banner
Version: 0.1.5
Summary: Display Banner text
Author: Sukhbinder Singh
License: Apache-2.0
Project-URL: Homepage, https://github.com/sukhbinder/winzy-banner
Project-URL: Changelog, https://github.com/sukhbinder/winzy-banner/releases
Project-URL: Issues, https://github.com/sukhbinder/winzy-banner/issues
Project-URL: CI, https://github.com/sukhbinder/winzy-banner/actions
Classifier: License :: OSI Approved :: Apache Software License
License-File: LICENSE
Requires-Dist: winzy
Requires-Dist: customtkinter
Provides-Extra: test
Requires-Dist: pytest; extra == "test"
